olipy/__init__.py
olipy/alphabet.py
olipy/corpora.py
olipy/eater.py
olipy/ebooks.py
olipy/example.py
olipy/gibberish.py
olipy/gutenberg.py
olipy/ia.py
olipy/letterforms.py
olipy/markov.py
olipy/mosaic.py
olipy/pycorpora.py
olipy/queneau.py
olipy/randomness.py
olipy/tokenizer.py
olipy/typewriter.py
olipy/data/__init__.py
olipy/data/ids_for_old_project_gutenberg_filenames.json
olipy/data/corpora-olipy/games/bgg_board_games.json
olipy/data/corpora-olipy/geography/large_cities.json
olipy/data/corpora-olipy/geography/us_states.json
olipy/data/corpora-olipy/language/languages.json
olipy/data/corpora-olipy/language/unicode_code_sheets.json
olipy/data/corpora-olipy/science/minor_planet_details.json
olipy/data/corpora-olipy/words/adjectives.json
olipy/data/corpora-olipy/words/by_syllable_count.json
olipy/data/corpora-olipy/words/common_nouns.json
olipy/data/corpora-olipy/words/common_verbs.json
olipy/data/corpora-olipy/words/common_words.json
olipy/data/corpora-olipy/words/ending.py
olipy/data/corpora-olipy/words/english_words.json
olipy/data/corpora-olipy/words/scribblenauts.json
olipy/data/corpora-olipy/words/literature/gutenberg_id_mapping.json
olipy/data/corpora-olipy/words/literature/fiction/pride_and_prejudice.json
olipy/data/corpora-olipy/words/literature/nonfiction/apollo_11.json
olipy/data/corpora-olipy/words/literature/nonfiction/literary_shrines.json
olipy/data/corpora-original/data/animals/ant_anatomy.json
olipy/data/corpora-original/data/animals/birds_antarctica.json
olipy/data/corpora-original/data/animals/birds_north_america.json
olipy/data/corpora-original/data/animals/cats.json
olipy/data/corpora-original/data/animals/cephalopod_anatomy.json
olipy/data/corpora-original/data/animals/collateral_adjectives.json
olipy/data/corpora-original/data/animals/common.json
olipy/data/corpora-original/data/animals/dinosaurs.json
olipy/data/corpora-original/data/animals/dog_names.json
olipy/data/corpora-original/data/animals/dogs-en-de.json
olipy-1.0.5.dist-info/METADATA
olipy-1.0.5.dist-info/WHEEL
olipy-1.0.5.dist-info/entry_points.txt
olipy-1.0.5.dist-info/licenses/LICENSE
olipy-1.0.5.dist-info/RECORD
