Metadata-Version: 2.4
Name: olipy
Version: 1.0.5
Summary: Library for artistic text generation
Project-URL: Homepage, https://github.com/leonardr/olipy/
Author-email: Leonard Richardson <leonardr@segfault.org>
License-Expression: GPL-3.0-or-later
License-File: LICENSE
Keywords: art supplies
Classifier: License :: OSI Approved :: GNU General Public License v3 or later (GPLv3+)
Classifier: Programming Language :: Python :: 3
Classifier: Programming Language :: Python :: Implementation :: CPython
Classifier: Topic :: Artistic Software
Classifier: Topic :: Text Processing
Requires-Python: >=3.9.0
Requires-Dist: beautifulsoup4
Requires-Dist: requests
Requires-Dist: syllables
Requires-Dist: textblob
Requires-Dist: wordfilter
Provides-Extra: internetarchive
Requires-Dist: internetarchive; extra == 'internetarchive'
